flet_routed_app/__init__.py
flet_routed_app/app.py
flet_routed_app/auth.py
flet_routed_app/page_not_found.py
flet_routed_app/routing.py
flet_routed_app/state.py
flet_routed_app/view_builder.py
flet_routed_app-0.3.4.dist-info/METADATA
flet_routed_app-0.3.4.dist-info/WHEEL
flet_routed_app-0.3.4.dist-info/LICENSE
flet_routed_app-0.3.4.dist-info/RECORD
