Metadata-Version: 2.1
Name: flet-routed-app
Version: 0.3.4
Summary: Tools to build flet apps with multiple views/routes
Home-page: https://github.com/iron3oxide/flet-routed-app
License: Apache-2.0
Author: iron3oxide
Author-email: jason.hottelet@tuta.io
Requires-Python: >=3.10,<4.0
Classifier: License :: OSI Approved :: Apache Software License
Classifier: Programming Language :: Python :: 3
Classifier: Programming Language :: Python :: 3.10
Classifier: Programming Language :: Python :: 3.11
Requires-Dist: flet (>=0.4.0,<0.5.0)
Requires-Dist: repath (>=0.9.0,<0.10.0)
Project-URL: Repository, https://github.com/iron3oxide/flet-routed-app
